flowchat/__init__.py
flowchat/__init__.pyi
flowchat/autodedent.py
flowchat/autodedent.pyi
flowchat/chain.py
flowchat/chain.pyi
flowchat/types.py
flowchat/types.pyi
flowchat/private/__init__.py
flowchat/private/__init__.pyi
flowchat/private/_private_helpers.py
flowchat/private/_private_helpers.pyi
flowchat-1.4.0.dist-info/LICENSE
flowchat-1.4.0.dist-info/METADATA
flowchat-1.4.0.dist-info/WHEEL
flowchat-1.4.0.dist-info/top_level.txt
flowchat-1.4.0.dist-info/RECORD
