Metadata-Version: 2.1
Name: flowchat
Version: 1.4.0
Summary: Streamlining the process of multi-prompting LLMs with chains
Home-page: https://github.com/flatypus/flowchat
Author: Hinson Chan
Author-email: <yhc3141@gmail.com>
Maintainer: Hinson Chan
Maintainer-email: <yhc3141@gmail.com>
License: MIT
Project-URL: Repository, https://github.com/flatypus/flowchat
Project-URL: Issues, https://github.com/flatypus/flowchat/issues
Keywords: openai gpt3 gpt-3 gpt4 gpt-4 chatbot ai nlp prompt prompt-engineering toolkit
Classifier: License :: OSI Approved :: MIT License
Classifier: Operating System :: OS Independent
Classifier: Programming Language :: Python :: 3
Classifier: Topic :: Scientific/Engineering :: Artificial Intelligence
Classifier: Topic :: Software Development :: Libraries :: Python Modules
License-File: LICENSE
Requires-Dist: openai
Requires-Dist: Pillow
Requires-Dist: requests
